drow_onimage.py
drow_onimage-0.0.4.dist-info/METADATA
drow_onimage-0.0.4.dist-info/WHEEL
drow_onimage-0.0.4.dist-info/entry_points.txt
drow_onimage-0.0.4.dist-info/top_level.txt
drow_onimage-0.0.4.dist-info/RECORD
