Metadata-Version: 2.1
Name: drow_onimage
Version: 0.0.4
Summary: You can draw on any image
Home-page: https://github.com/YTsubono/drow_onimage
Author: yohei tsubono
Author-email: s2122040@stu.musashino-u.ac.jp
Project-URL: Bug Tracker, https://github.com/YTsubono/drow_onimage
Classifier: Programming Language :: Python :: 3
Classifier: License :: OSI Approved :: MIT License
Classifier: Operating System :: OS Independent
Requires-Python: <=3.11
